huaweicloudsdkelb/__init__.py
huaweicloudsdkelb/v2/__init__.py
huaweicloudsdkelb/v2/elb_async_client.py
huaweicloudsdkelb/v2/elb_client.py
huaweicloudsdkelb/v2/model/__init__.py
huaweicloudsdkelb/v2/model/action_match.py
huaweicloudsdkelb/v2/model/action_tag.py
huaweicloudsdkelb/v2/model/batch_create_listener_tags_request.py
huaweicloudsdkelb/v2/model/batch_create_listener_tags_request_body.py
huaweicloudsdkelb/v2/model/batch_create_listener_tags_response.py
huaweicloudsdkelb/v2/model/batch_create_loadbalancer_tags_request.py
huaweicloudsdkelb/v2/model/batch_create_loadbalancer_tags_request_body.py
huaweicloudsdkelb/v2/model/batch_create_loadbalancer_tags_response.py
huaweicloudsdkelb/v2/model/batch_delete_listener_tags_request.py
huaweicloudsdkelb/v2/model/batch_delete_listener_tags_request_body.py
huaweicloudsdkelb/v2/model/batch_delete_listener_tags_response.py
huaweicloudsdkelb/v2/model/batch_delete_loadbalancer_tags_request.py
huaweicloudsdkelb/v2/model/batch_delete_loadbalancer_tags_request_body.py
huaweicloudsdkelb/v2/model/batch_delete_loadbalancer_tags_response.py
huaweicloudsdkelb/v2/model/certificate_resp.py
huaweicloudsdkelb/v2/model/create_certificate_request.py
huaweicloudsdkelb/v2/model/create_certificate_request_body.py
huaweicloudsdkelb/v2/model/create_certificate_response.py
huaweicloudsdkelb/v2/model/create_healthmonitor_req.py
huaweicloudsdkelb/v2/model/create_healthmonitor_request.py
huaweicloudsdkelb/v2/model/create_healthmonitor_request_body.py
huaweicloudsdkelb/v2/model/create_healthmonitor_response.py
huaweicloudsdkelb/v2/model/create_l7policy_req.py
huaweicloudsdkelb/v2/model/create_l7policy_request.py
huaweicloudsdkelb/v2/model/create_l7policy_request_body.py
huaweicloudsdkelb/v2/model/create_l7policy_response.py
huaweicloudsdkelb/v2/model/create_l7rule_req.py
huaweicloudsdkelb/v2/model/create_l7rule_req_in_policy.py
huaweicloudsdkelb/v2/model/create_l7rule_request.py
huaweicloudsdkelb/v2/model/create_l7rule_request_body.py
huaweicloudsdkelb-3.1.184.dist-info/METADATA
huaweicloudsdkelb-3.1.184.dist-info/WHEEL
huaweicloudsdkelb-3.1.184.dist-info/licenses/LICENSE
huaweicloudsdkelb-3.1.184.dist-info/RECORD
